subprocesslib/__init__.py
subprocesslib/command.py
subprocesslib/paramspec_from.py
subprocesslib/py.typed
subprocesslib-0.1.0.dist-info/WHEEL
subprocesslib-0.1.0.dist-info/METADATA
subprocesslib-0.1.0.dist-info/RECORD
