Metadata-Version: 2.4
Name: subprocesslib
Version: 0.1.0
Summary: Object-oriented subprocess
Author: Antoine Cezar
Author-email: Antoine Cezar <antoine@cezar.fr>
License-Expression: MIT
Classifier: Development Status :: 4 - Beta
Classifier: Intended Audience :: Developers
Classifier: License :: OSI Approved :: MIT License
Classifier: Programming Language :: Python :: 3.12
Classifier: Topic :: Software Development :: Libraries :: Python Modules
Classifier: Topic :: Utilities
Classifier: Typing :: Typed
Requires-Python: >=3.12
Project-URL: Changelog, https://gitlab.com/chwitlabs/subprocesslib/-/blob/main/CHANGELOG.md
Project-URL: Documentation, https://gitlab.com/chwitlabs/subprocesslib
Project-URL: Homepage, https://gitlab.com/chwitlabs/subprocesslib
Project-URL: Issues, https://gitlab.com/chwitlabs/subprocesslib/-/issues
Project-URL: Repository, https://gitlab.com/chwitlabs/subprocesslib
